{
  "_class": "shapePath",
  "booleanOperation": -1,
  "clippingMaskMode": 0,
  "do_objectID": "A3F86D1C-667E-40F3-AC16-D96ECE013449",
  "edited": true,
  "exportOptions": {
    "_class": "exportOptions",
    "do_objectID": "156B5D6D-DCEF-4D8F-A80F-C0DAF2F57BAC",
    "exportFormats": [
    ],
    "includedLayerIds": [
    ],
    "layerOptions": 0,
    "shouldTrim": false
  },
  "frame": {
    "_class": "rect",
    "constrainProportions": false,
    "do_objectID": "F72E8AA6-B588-44B4-B707-CA2787AB7562",
    "height": 15.96774193548387,
    "width": 22,
    "x": 0,
    "y": 0
  },
  "hasClippingMask": false,
  "isClosed": true,
  "isFixedToViewport": false,
  "isFlippedHorizontal": false,
  "isFlippedVertical": false,
  "isLocked": false,
  "isVisible": true,
  "layerListExpandedType": 0,
  "name": "Path",
  "nameIsFixed": false,
  "pointRadiusBehaviour": 1,
  "points": [
    {
      "_class": "curvePoint",
      "cornerRadius": 0,
      "curveFrom": "{0, 0}",
      "curveMode": 1,
      "curveTo": "{0, 0}",
      "hasCurveFrom": false,
      "hasCurveTo": false,
      "point": "{0, 0}"
    },
    {
      "_class": "curvePoint",
      "cornerRadius": 0,
      "curveFrom": "{0, 0.089244444444444446}",
      "curveMode": 1,
      "curveTo": "{0, 0.089244444444444446}",
      "hasCurveFrom": false,
      "hasCurveTo": false,
      "point": "{0, 0.089244444444444446}"
    },
    {
      "_class": "curvePoint",
      "cornerRadius": 0,
      "curveFrom": "{0.93548387096774188, 0.089244444444444446}",
      "curveMode": 1,
      "curveTo": "{0.93548387096774188, 0.089244444444444446}",
      "hasCurveFrom": false,
      "hasCurveTo": false,
      "point": "{0.93548387096774188, 0.089244444444444446}"
    },
    {
      "_class": "curvePoint",
      "cornerRadius": 0,
      "curveFrom": "{0.93548387096774188, 0.35699999999999993}",
      "curveMode": 1,
      "curveTo": "{0.93548387096774188, 0.35699999999999993}",
      "hasCurveFrom": false,
      "hasCurveTo": false,
      "point": "{0.93548387096774188, 0.35699999999999993}"
    },
    {
      "_class": "curvePoint",
      "cornerRadius": 0,
      "curveFrom": "{0.80645161290322576, 0.35699999999999993}",
      "curveMode": 1,
      "curveTo": "{0.80645161290322576, 0.35699999999999993}",
      "hasCurveFrom": false,
      "hasCurveTo": false,
      "point": "{0.80645161290322576, 0.35699999999999993}"
    },
    {
      "_class": "curvePoint",
      "cornerRadius": 0,
      "curveFrom": "{0.80645161290322576, 0.26775555555555552}",
      "curveMode": 1,
      "curveTo": "{0.80645161290322576, 0.26775555555555552}",
      "hasCurveFrom": false,
      "hasCurveTo": false,
      "point": "{0.80645161290322576, 0.26775555555555552}"
    },
    {
      "_class": "curvePoint",
      "cornerRadius": 0,
      "curveFrom": "{0.87096774193548387, 0.26775555555555552}",
      "curveMode": 1,
      "curveTo": "{0.87096774193548387, 0.26775555555555552}",
      "hasCurveFrom": false,
      "hasCurveTo": false,
      "point": "{0.87096774193548387, 0.26775555555555552}"
    },
    {
      "_class": "curvePoint",
      "cornerRadius": 0,
      "curveFrom": "{0.8725806451612903, 0.17851111111111115}",
      "curveMode": 4,
      "curveTo": "{0.87096774193548387, 0.17851111111111115}",
      "hasCurveFrom": true,
      "hasCurveTo": false,
      "point": "{0.87096774193548387, 0.17851111111111115}"
    },
    {
      "_class": "curvePoint",
      "cornerRadius": 0,
      "curveFrom": "{0.12903225806451613, 0.17851111111111115}",
      "curveMode": 4,
      "curveTo": "{0.85000000000000009, 0.17808888888888896}",
      "hasCurveFrom": false,
      "hasCurveTo": true,
      "point": "{0.12903225806451613, 0.17851111111111115}"
    },
    {
      "_class": "curvePoint",
      "cornerRadius": 0,
      "curveFrom": "{0.12903225806451613, 0.26775555555555552}",
      "curveMode": 1,
      "curveTo": "{0.12903225806451613, 0.26775555555555552}",
      "hasCurveFrom": false,
      "hasCurveTo": false,
      "point": "{0.12903225806451613, 0.26775555555555552}"
    },
    {
      "_class": "curvePoint",
      "cornerRadius": 0,
      "curveFrom": "{0.19354838709677419, 0.26775555555555552}",
      "curveMode": 1,
      "curveTo": "{0.19354838709677419, 0.26775555555555552}",
      "hasCurveFrom": false,
      "hasCurveTo": false,
      "point": "{0.19354838709677419, 0.26775555555555552}"
    },
    {
      "_class": "curvePoint",
      "cornerRadius": 0,
      "curveFrom": "{0.19354838709677419, 0.35699999999999993}",
      "curveMode": 1,
      "curveTo": "{0.19354838709677419, 0.35699999999999993}",
      "hasCurveFrom": false,
      "hasCurveTo": false,
      "point": "{0.19354838709677419, 0.35699999999999993}"
    },
    {
      "_class": "curvePoint",
      "cornerRadius": 0,
      "curveFrom": "{0.064516129032258063, 0.35699999999999993}",
      "curveMode": 1,
      "curveTo": "{0.064516129032258063, 0.35699999999999993}",
      "hasCurveFrom": false,
      "hasCurveTo": false,
      "point": "{0.064516129032258063, 0.35699999999999993}"
    },
    {
      "_class": "curvePoint",
      "cornerRadius": 0,
      "curveFrom": "{0.064516129032258063, 0.17851111111111106}",
      "curveMode": 1,
      "curveTo": "{0.064516129032258063, 0.17851111111111106}",
      "hasCurveFrom": false,
      "hasCurveTo": false,
      "point": "{0.064516129032258063, 0.17851111111111106}"
    },
    {
      "_class": "curvePoint",
      "cornerRadius": 0,
      "curveFrom": "{0, 0.17851111111111106}",
      "curveMode": 1,
      "curveTo": "{0, 0.17851111111111106}",
      "hasCurveFrom": false,
      "hasCurveTo": false,
      "point": "{0, 0.17851111111111106}"
    },
    {
      "_class": "curvePoint",
      "cornerRadius": 0,
      "curveFrom": "{0, 0.44624444444444433}",
      "curveMode": 1,
      "curveTo": "{0, 0.44624444444444433}",
      "hasCurveFrom": false,
      "hasCurveTo": false,
      "point": "{0, 0.44624444444444433}"
    },
    {
      "_class": "curvePoint",
      "cornerRadius": 0,
      "curveFrom": "{0.19354838709677419, 0.44624444444444433}",
      "curveMode": 1,
      "curveTo": "{0.19354838709677419, 0.44624444444444433}",
      "hasCurveFrom": false,
      "hasCurveTo": false,
      "point": "{0.19354838709677419, 0.44624444444444433}"
    },
    {
      "_class": "curvePoint",
      "cornerRadius": 0,
      "curveFrom": "{0.19354838709677419, 1}",
      "curveMode": 1,
      "curveTo": "{0.19354838709677419, 1}",
      "hasCurveFrom": false,
      "hasCurveTo": false,
      "point": "{0.19354838709677419, 1}"
    },
    {
      "_class": "curvePoint",
      "cornerRadius": 0,
      "curveFrom": "{0.80645161290322576, 1}",
      "curveMode": 1,
      "curveTo": "{0.80645161290322576, 1}",
      "hasCurveFrom": false,
      "hasCurveTo": false,
      "point": "{0.80645161290322576, 1}"
    },
    {
      "_class": "curvePoint",
      "cornerRadius": 0,
      "curveFrom": "{0.80645161290322576, 0.44624444444444444}",
      "curveMode": 1,
      "curveTo": "{0.80645161290322576, 0.44624444444444444}",
      "hasCurveFrom": false,
      "hasCurveTo": false,
      "point": "{0.80645161290322576, 0.44624444444444444}"
    },
    {
      "_class": "curvePoint",
      "cornerRadius": 0,
      "curveFrom": "{1, 0.44624444444444444}",
      "curveMode": 1,
      "curveTo": "{1, 0.44624444444444444}",
      "hasCurveFrom": false,
      "hasCurveTo": false,
      "point": "{1, 0.44624444444444444}"
    },
    {
      "_class": "curvePoint",
      "cornerRadius": 0,
      "curveFrom": "{1, 0}",
      "curveMode": 1,
      "curveTo": "{1, 0}",
      "hasCurveFrom": false,
      "hasCurveTo": false,
      "point": "{1, 0}"
    }
  ],
  "resizingConstraint": 63,
  "resizingType": 0,
  "rotation": 0,
  "shouldBreakMaskChain": false,
  "style": {
    "_class": "style",
    "blur": {
      "_class": "blur",
      "center": "{0.5, 0.5}",
      "do_objectID": "009FBC12-160A-423B-92D6-D2040FE3A5C4",
      "isEnabled": false,
      "motionAngle": 0,
      "radius": 80,
      "saturation": 1,
      "type": 0
    },
    "do_objectID": "1E2446C3-5E93-4DD9-ABF8-3B0DB81E90AC",
    "endMarkerType": 0,
    "miterLimit": 10,
    "startMarkerType": 0,
    "windingRule": 1
  }
}