{
  "_class": "shapePath",
  "booleanOperation": -1,
  "clippingMaskMode": 0,
  "do_objectID": "E2EFC64F-3E3E-4F17-B636-24E733E14E22",
  "edited": true,
  "exportOptions": {
    "_class": "exportOptions",
    "do_objectID": "5F866D1F-9B28-4F72-A283-C0DC00399B0A",
    "exportFormats": [
    ],
    "includedLayerIds": [
    ],
    "layerOptions": 0,
    "shouldTrim": false
  },
  "frame": {
    "_class": "rect",
    "constrainProportions": false,
    "do_objectID": "D513F421-0364-490A-AD39-EB223C656E55",
    "height": 11.95512,
    "width": 3.406298089171973,
    "x": 0.06372229299362912,
    "y": 0.04488000000000056
  },
  "hasClippingMask": false,
  "isClosed": true,
  "isFixedToViewport": false,
  "isFlippedHorizontal": false,
  "isFlippedVertical": false,
  "isLocked": false,
  "isVisible": true,
  "layerListExpandedType": 0,
  "name": "Fill 17",
  "nameIsFixed": false,
  "pointRadiusBehaviour": 1,
  "points": [
    {
      "_class": "curvePoint",
      "cornerRadius": 0,
      "curveFrom": "{0, 0.25465239997590988}",
      "curveMode": 1,
      "curveTo": "{0, 0.25465239997590988}",
      "hasCurveFrom": false,
      "hasCurveTo": false,
      "point": "{0, 0.25465239997590988}"
    },
    {
      "_class": "curvePoint",
      "cornerRadius": 0,
      "curveFrom": "{0, 0.72004630651971702}",
      "curveMode": 1,
      "curveTo": "{0, 0.72004630651971702}",
      "hasCurveFrom": false,
      "hasCurveTo": false,
      "point": "{0, 0.72004630651971702}"
    },
    {
      "_class": "curvePoint",
      "cornerRadius": 0,
      "curveFrom": "{0.43945422940794654, 1}",
      "curveMode": 4,
      "curveTo": "{0, 1}",
      "hasCurveFrom": true,
      "hasCurveTo": false,
      "point": "{0, 1}"
    },
    {
      "_class": "curvePoint",
      "cornerRadius": 0,
      "curveFrom": "{0.94287576703177001, 0.80891868923105748}",
      "curveMode": 4,
      "curveTo": "{0.81199606274477043, 0.91989373590562029}",
      "hasCurveFrom": false,
      "hasCurveTo": true,
      "point": "{0.94287576703177001, 0.80891868923105748}"
    },
    {
      "_class": "curvePoint",
      "cornerRadius": 0,
      "curveFrom": "{0.97536597625081167, 0.78136898667683807}",
      "curveMode": 4,
      "curveTo": "{0.94287576703177001, 0.80891868923105748}",
      "hasCurveFrom": true,
      "hasCurveTo": false,
      "point": "{0.94287576703177001, 0.80891868923105748}"
    },
    {
      "_class": "curvePoint",
      "cornerRadius": 0,
      "curveFrom": "{0.99320142830216496, 0.72135787846546084}",
      "curveMode": 4,
      "curveTo": "{0.99320142830216496, 0.75195899330161464}",
      "hasCurveFrom": false,
      "hasCurveTo": true,
      "point": "{0.99320142830216496, 0.72135787846546084}"
    },
    {
      "_class": "curvePoint",
      "cornerRadius": 0,
      "curveFrom": "{0.99320142830216496, 0.72135787846546084}",
      "curveMode": 1,
      "curveTo": "{0.99320142830216496, 0.72135787846546084}",
      "hasCurveFrom": false,
      "hasCurveTo": false,
      "point": "{0.99320142830216496, 0.72135787846546084}"
    },
    {
      "_class": "curvePoint",
      "cornerRadius": 0,
      "curveFrom": "{0.99320142830216496, 0.21319735811936635}",
      "curveMode": 4,
      "curveTo": "{0.99320142830216496, 0.22123408213384721}",
      "hasCurveFrom": true,
      "hasCurveTo": false,
      "point": "{0.99320142830216496, 0.22123408213384721}"
    },
    {
      "_class": "curvePoint",
      "cornerRadius": 0,
      "curveFrom": "{0.9952040880437284, 0.19725774396241941}",
      "curveMode": 4,
      "curveTo": "{0.9938611279817372, 0.20520078426648997}",
      "hasCurveFrom": false,
      "hasCurveTo": true,
      "point": "{0.9952040880437284, 0.19725774396241941}"
    },
    {
      "_class": "curvePoint",
      "cornerRadius": 0,
      "curveFrom": "{1.0059948899453381, 0.13307771063778534}",
      "curveMode": 4,
      "curveTo": "{0.9952040880437284, 0.19725774396241941}",
      "hasCurveFrom": true,
      "hasCurveTo": false,
      "point": "{0.9952040880437284, 0.19725774396241941}"
    },
    {
      "_class": "curvePoint",
      "cornerRadius": 0,
      "curveFrom": "{0.9952040880437284, 0}",
      "curveMode": 4,
      "curveTo": "{0.9952040880437284, 0}",
      "hasCurveFrom": false,
      "hasCurveTo": true,
      "point": "{0.9952040880437284, 0}"
    },
    {
      "_class": "curvePoint",
      "cornerRadius": 0,
      "curveFrom": "{0.9952040880437284, 0}",
      "curveMode": 1,
      "curveTo": "{0.9952040880437284, 0}",
      "hasCurveFrom": false,
      "hasCurveTo": false,
      "point": "{0.9952040880437284, 0}"
    }
  ],
  "resizingConstraint": 63,
  "resizingType": 0,
  "rotation": 0,
  "shouldBreakMaskChain": false,
  "style": {
    "_class": "style",
    "do_objectID": "4EA8596F-E94A-4DF5-9F5B-9FE7713CFB0B",
    "endMarkerType": 0,
    "fills": [
      {
        "_class": "fill",
        "color": {
          "_class": "color",
          "alpha": 1,
          "blue": 0.847,
          "green": 0.847,
          "red": 0.847
        },
        "fillType": 1,
        "gradient": {
          "_class": "gradient",
          "elipseLength": 0,
          "from": "{0.50000646558043094, 1}",
          "gradientType": 0,
          "stops": [
            {
              "_class": "gradientStop",
              "color": {
                "_class": "color",
                "alpha": 1,
                "blue": 0.1372549019607843,
                "green": 0.1490196078431373,
                "red": 0.7764705882352941
              },
              "position": 0
            },
            {
              "_class": "gradientStop",
              "color": {
                "_class": "color",
                "alpha": 1,
                "blue": 0.1019607843137255,
                "green": 0.1019607843137255,
                "red": 0.5372549019607843
              },
              "position": 1
            }
          ],
          "to": "{0.50000646558043094, 1.8689900226067158e-06}"
        },
        "isEnabled": true,
        "noiseIndex": 0,
        "noiseIntensity": 0,
        "patternFillType": 1,
        "patternTileScale": 1
      }
    ],
    "miterLimit": 10,
    "startMarkerType": 0,
    "windingRule": 1
  }
}