{
  "_class": "sharedStyle",
  "do_objectID": "62D3F9BD-261D-4A20-AE01-4387ED77CE9F",
  "name": "Big/Dark/50px/Regular/Centered",
  "value": {
    "_class": "style",
    "blur": {
      "_class": "blur",
      "center": "{0.5, 0.5}",
      "isEnabled": false,
      "motionAngle": 0,
      "radius": 10,
      "saturation": 1,
      "type": 0
    },
    "borderOptions": {
      "_class": "borderOptions",
      "dashPattern": [
      ],
      "isEnabled": true,
      "lineCapStyle": 0,
      "lineJoinStyle": 0
    },
    "borders": [
    ],
    "colorControls": {
      "_class": "colorControls",
      "brightness": 0,
      "contrast": 1,
      "hue": 0,
      "isEnabled": false,
      "saturation": 1
    },
    "contextSettings": {
      "_class": "graphicsContextSettings",
      "blendMode": 0,
      "opacity": 1
    },
    "do_objectID": "D98E1EC7-362E-4882-887F-54D7815B6D58",
    "endMarkerType": 0,
    "fills": [
    ],
    "innerShadows": [
    ],
    "miterLimit": 10,
    "shadows": [
    ],
    "startMarkerType": 0,
    "textStyle": {
      "_class": "textStyle",
      "encodedAttributes": {
        "MSAttributedStringColorAttribute": {
          "_class": "color",
          "alpha": 1,
          "blue": 0.3215686275,
          "green": 0.2509803922,
          "red": 0.2078431373
        },
        "MSAttributedStringFontAttribute": {
          "_class": "fontDescriptor",
          "attributes": {
            "name": "SourceSansPro-Regular",
            "size": 50
          }
        },
        "paragraphStyle": {
          "_class": "paragraphStyle",
          "alignment": 2,
          "allowsDefaultTighteningForTruncation": 0,
          "maximumLineHeight": 60,
          "minimumLineHeight": 60
        }
      },
      "verticalAlignment": 0
    },
    "windingRule": 1
  }
}