{
  "_class": "shapePath",
  "booleanOperation": -1,
  "clippingMaskMode": 0,
  "do_objectID": "CFE2AC50-E106-45C6-A84D-AE56A85CF5B8",
  "edited": true,
  "exportOptions": {
    "_class": "exportOptions",
    "do_objectID": "E594EDAE-EF6A-4A9F-BD1B-9FC08A3B04EA",
    "exportFormats": [
    ],
    "includedLayerIds": [
    ],
    "layerOptions": 0,
    "shouldTrim": false
  },
  "frame": {
    "_class": "rect",
    "constrainProportions": false,
    "do_objectID": "E4D640A0-2B43-4E82-87FA-3B794FDB9430",
    "height": 1.076250000000001,
    "width": 0.3478125000000007,
    "x": 2.204999999999999,
    "y": 3.015468750000001
  },
  "hasClippingMask": false,
  "isClosed": true,
  "isFixedToViewport": false,
  "isFlippedHorizontal": false,
  "isFlippedVertical": false,
  "isLocked": false,
  "isVisible": true,
  "layerListExpandedType": 0,
  "name": "Path",
  "nameIsFixed": false,
  "pointRadiusBehaviour": 1,
  "points": [
    {
      "_class": "curvePoint",
      "cornerRadius": 0,
      "curveFrom": "{0, 1}",
      "curveMode": 1,
      "curveTo": "{0, 1}",
      "hasCurveFrom": false,
      "hasCurveTo": false,
      "point": "{0, 1}"
    },
    {
      "_class": "curvePoint",
      "cornerRadius": 0,
      "curveFrom": "{0.066037735849050025, 0.91463414634146312}",
      "curveMode": 1,
      "curveTo": "{0.066037735849050025, 0.91463414634146312}",
      "hasCurveFrom": false,
      "hasCurveTo": false,
      "point": "{0.066037735849050025, 0.91463414634146312}"
    },
    {
      "_class": "curvePoint",
      "cornerRadius": 0,
      "curveFrom": "{0.056603773584907681, 0.91463414634146312}",
      "curveMode": 1,
      "curveTo": "{0.056603773584907681, 0.91463414634146312}",
      "hasCurveFrom": false,
      "hasCurveTo": false,
      "point": "{0.056603773584907681, 0.91463414634146312}"
    },
    {
      "_class": "curvePoint",
      "cornerRadius": 0,
      "curveFrom": "{0.38679245283018465, 0}",
      "curveMode": 1,
      "curveTo": "{0.38679245283018465, 0}",
      "hasCurveFrom": false,
      "hasCurveTo": false,
      "point": "{0.38679245283018465, 0}"
    },
    {
      "_class": "curvePoint",
      "cornerRadius": 0,
      "curveFrom": "{0.65094339622641151, 0}",
      "curveMode": 1,
      "curveTo": "{0.65094339622641151, 0}",
      "hasCurveFrom": false,
      "hasCurveTo": false,
      "point": "{0.65094339622641151, 0}"
    },
    {
      "_class": "curvePoint",
      "cornerRadius": 0,
      "curveFrom": "{1, 0.3993902439024396}",
      "curveMode": 1,
      "curveTo": "{1, 0.3993902439024396}",
      "hasCurveFrom": false,
      "hasCurveTo": false,
      "point": "{1, 0.3993902439024396}"
    }
  ],
  "resizingConstraint": 63,
  "resizingType": 0,
  "rotation": 0,
  "shouldBreakMaskChain": false,
  "style": {
    "_class": "style",
    "do_objectID": "6E8C1824-D970-40F5-A13B-7A36B6B789E8",
    "endMarkerType": 0,
    "miterLimit": 10,
    "startMarkerType": 0,
    "windingRule": 1
  }
}